stargaze.py
stargaze-0.0.2.dist-info/METADATA
stargaze-0.0.2.dist-info/RECORD
stargaze-0.0.2.dist-info/WHEEL
stargaze-0.0.2.dist-info/entry_points.txt
stargaze-0.0.2.dist-info/top_level.txt
