Metadata-Version: 2.1
Name: stargaze
Version: 0.0.2
Summary: Parse and query stardict dictionary files.
Home-page: https://github.com/codito/stargaze
Author: Arun Mahapatra
Author-email: arun@codito.in
License: MIT
Platform: UNKNOWN
Classifier: License :: OSI Approved :: MIT License
Classifier: Programming Language :: Python
Classifier: Programming Language :: Python :: 3
Classifier: Programming Language :: Python :: 3.6
Classifier: Programming Language :: Python :: Implementation :: CPython
Classifier: Programming Language :: Python :: Implementation :: PyPy
Requires-Dist: click (>=6.7)
Requires-Dist: python-idzip (>=0.3)
